[
  {
    "employeeId": "EMP001",
    "name": "Niraj Maskey",
    "address": "Patan Dhoka-16, Lalitpur, Nepal",
    "position": "Marketing",
    "basicSalary": 65000,
    "currency": "Rs",
    "joiningDate": "2023-01-01",
    "status": "active",
    "contractSent": false
  },
  {
    "employeeId": "EMP002",
    "name": "Shreeya Khadka",
    "address": "Changunarayan-3, Bhaktapur, Nepal",
    "position": "QA Engineer",
    "basicSalary": 25000,
    "currency": "Rs",
    "joiningDate": "2023-01-01",
    "status": "active",
    "contractSent": false
  },
  {
    "employeeId": "EMP003",
    "name": "Sujan Baskota",
    "address": "Kathmandu, Nepal",
    "position": "Junior Developer",
    "basicSalary": 35000,
    "currency": "Rs",
    "joiningDate": "2023-01-01",
    "status": "active",
    "contractSent": false
  },
  {
    "employeeId": "EMP004",
    "name": "Elisha Dongol",
    "address": "Bhaktapur, Nepal",
    "position": "Project Manager and Tester",
    "basicSalary": 130000,
    "currency": "Rs",
    "joiningDate": "2023-01-01",
    "status": "active",
    "contractSent": false
  },
  {
    "employeeId": "EMP005",
    "name": "Salon Poudel",
    "address": "Lalitpur, Nepal",
    "position": "UI/UX Designer",
    "basicSalary": 35000,
    "currency": "Rs",
    "joiningDate": "2023-01-01",
    "status": "active",
    "contractSent": false
  }
]

